{
    "key": "group_67f6908239ff9",
    "title": "Block: Content Index",
    "fields": [],
    "location": [
        [
            {
                "param": "block",
                "operator": "==",
                "value": "acf\/ag-content-index"
            }
        ]
    ],
    "menu_order": 0,
    "position": "normal",
    "style": "default",
    "label_placement": "top",
    "instruction_placement": "label",
    "hide_on_screen": "",
    "active": true,
    "description": "",
    "show_in_rest": 0,
    "modified": 1744212124
}
